{
  "unversionedId": "mp-video-view",
  "id": "mp-video-view",
  "isDocsHomePage": false,
  "title": "MPVideoView",
  "description": "可用于视频播放，根据浏览器、微信小程序支持不同格式播放。",
  "source": "@site/../docs/MPVideoView.md",
  "slug": "/mp-video-view",
  "permalink": "/zh/docs/mp-video-view",
  "editUrl": "https://github.com/mpflutter/mpflutter/edit/master/website/../docs/MPVideoView.md",
  "version": "current",
  "sidebar": "docs",
  "previous": {
    "title": "MPSliverWaterfall",
    "permalink": "/zh/docs/mp-sliver-waterfall"
  },
  "next": {
    "title": "MPWebView",
    "permalink": "/zh/docs/mp-web-view"
  }
}